Amazon_SDK/__init__.py
Amazon_SDK/amz_sdk.py
Amazon_SDK/order_statuses.py
amazon_sdk-0.0.7.dist-info/WHEEL
amazon_sdk-0.0.7.dist-info/METADATA
amazon_sdk-0.0.7.dist-info/RECORD
